{"background_harmonic_balance.md":"CQ1C4zKR","background_limit_cycles.md":"1K77pTNx","background_stability_response.md":"D28z5Jsq","examples_index.md":"CFNsoJEB","examples_parametric_via_three_wave_mixing.md":"DURi-CkZ","examples_parametron.md":"BSqtleoP","examples_state_dependent_perturbation.md":"XiSF-RNF","examples_wave_mixing.md":"CfcQOZWP","index.md":"C8R7Bzji","introduction_citation.md":"Dfz0nc5u","introduction_index.md":"Ddl3knfG","manual_api.md":"CF_O49I5","manual_entering_eom.md":"CzCdyrrB","manual_extracting_harmonics.md":"82BnXa-5","manual_krylov-bogoliubov_method.md":"CmgJPLIn","manual_linear_response.md":"fmSM1MoE","manual_methods.md":"CgP8OyEW","manual_plotting.md":"BVy0Gwug","manual_saving.md":"CISxEGvW","manual_solving_harmonics.md":"C47__-JJ","manual_time_dependent.md":"M0wKFRu2","tutorials_classification.md":"BJMdymyf","tutorials_index.md":"CcRvJ7lD","tutorials_limit_cycles.md":"DPcDSvRq","tutorials_linear_response.md":"CUKj_rb1","tutorials_steady_states.md":"CwAE8TaL","tutorials_time_dependent.md":"DT-jeDNl"}
